MANIFEST.in
README.rst
setup.py
django_kss/__init__.py
django_kss/admin.py
django_kss/models.py
django_kss/setup.py
django_kss/tests.py
django_kss/urls.py
django_kss/utils.py
django_kss/views.py
django_kss/pykss/__init__.py
django_kss/pykss/comment.py
django_kss/pykss/exceptions.py
django_kss/pykss/modifier.py
django_kss/pykss/parser.py
django_kss/pykss/section.py
django_kss/pykss/contrib/__init__.py
django_kss/pykss/contrib/django/__init__.py
django_kss/pykss/contrib/django/models.py
django_kss/pykss/contrib/django/views.py
django_kss/pykss/contrib/django/templatetags/__init__.py
django_kss/static/css/buttons.css
django_kss/static/css/forms.css
django_kss/static/css/layout.css
django_kss/static/js/kss.js
django_kss/templates/styleguide-full-content.html
django_kss/templates/styleguide-inline-content.html
django_kss/templates/styleguide.html
django_kss/templates/styleguide_base.html
django_kss/templates/prototype/hello.html
django_kss/templates/pykss/styleguideblock.html
django_kss/templatetags/__init__.py
django_kss/templatetags/kss_extra.py
django_kss/templatetags/pykss.py
django_kss_styleguide.egg-info/PKG-INFO
django_kss_styleguide.egg-info/SOURCES.txt
django_kss_styleguide.egg-info/dependency_links.txt
django_kss_styleguide.egg-info/requires.txt
django_kss_styleguide.egg-info/top_level.txt