Metadata-Version: 1.1
Name: django-kss-styleguide
Version: 0.5.6
Summary: A simple Django app to make styleguide
Home-page: https://github.com/timtan/django_kss
Author: Tim Hsu
Author-email: tim.yellow@gmail.com
License: BSD License
Platform: UNKNOWN
Classifier: Environment :: Web Environment
Classifier: Framework :: Django
Classifier: Intended Audience :: Developers
Classifier: License :: OSI Approved :: BSD License
Classifier: Operating System :: OS Independent
Classifier: Programming Language :: Python
Classifier: Topic :: Internet :: WWW/HTTP
Classifier: Topic :: Internet :: WWW/HTTP :: Dynamic Content
